pyrite/__init__.py
pyrite/each.py
pyritelib-0.1.0.dist-info/licenses/LICENSE
pyritelib-0.1.0.dist-info/METADATA
pyritelib-0.1.0.dist-info/WHEEL
pyritelib-0.1.0.dist-info/top_level.txt
pyritelib-0.1.0.dist-info/RECORD
