Metadata-Version: 2.4
Name: pyritelib
Version: 0.1.0
Summary: Library of various utilities that I use in my programmes.
Author-email: Ángel Moreno Prieto <angelmorenoprieto@gmail.com>
License: MIT
Project-URL: Homepage, https://github.com/angelmorenoprieto/pyrite
Requires-Python: >=3.10
License-File: LICENSE
Dynamic: license-file
